caerp_split_pdf/__init__.py
caerp_split_pdf/config.py
caerp_split_pdf/data_finder.py
caerp_split_pdf/errors.py
caerp_split_pdf/log_config.py
caerp_split_pdf/splitter.py
caerp_split_pdf/utils.py
caerp_split_pdf-2024.1.1.data/scripts/caerp-change-code-analytic
caerp_split_pdf-2024.1.1.data/scripts/caerp-split-pdf-page2text
caerp_split_pdf-2024.1.1.data/scripts/caerp-split-pdf-run
caerp_split_pdf-2024.1.1.dist-info/LICENSE.txt
caerp_split_pdf-2024.1.1.dist-info/METADATA
caerp_split_pdf-2024.1.1.dist-info/WHEEL
caerp_split_pdf-2024.1.1.dist-info/top_level.txt
caerp_split_pdf-2024.1.1.dist-info/RECORD
