Metadata-Version: 2.1
Name: caerp_split_pdf
Version: 2024.1.1
Summary: Splits specific PDF files and stores the result in a custom directory layout
Author: Arezki Feth
Author-email: tech@majerti.fr
License: GPLv3
Classifier: Programming Language :: Python
Classifier: License :: OSI Approved :: GNU General Public License (GPL)
Classifier: Operating System :: OS Independent
Requires-Python: >=3.7
License-File: LICENSE.txt
Requires-Dist: pyyaml
Requires-Dist: PyPDF4
Requires-Dist: mailinglogger
Provides-Extra: dev
Requires-Dist: pytest ; extra == 'dev'
